urax_adb-2.0.4.dist-info/METADATA
urax_adb-2.0.4.dist-info/WHEEL
urax_adb-2.0.4.dist-info/entry_points.txt
urax_adb-2.0.4.dist-info/licenses/LICENSE
urax_adb/__init__.py
urax_adb-2.0.4.dist-info/RECORD
