Metadata-Version: 2.1
Name: urax_adb
Version: 2.0.4
Summary: A Python library to interact with Android devices using ADB.
Author-Email: Nguyen Thai Minh <ntm09112012@gmail.com>
License: Copyright (c) 2025 Nguyen Thai Minh
Classifier: Programming Language :: Python :: 3
Classifier: License :: OSI Approved :: MIT License
Classifier: Operating System :: OS Independent
Classifier: Development Status :: 4 - Beta
Project-URL: Homepage, https://github.com/thaiminhnguyen1999/urax_adb
Project-URL: Issues, https://github.com/thaiminhnguyen1999/urax_adb/issues
Requires-Python: >=3.8
